codemanip/__init__.py
codemanip/amalgamated_header.py
codemanip/code_position.py
codemanip/code_replacements.py
codemanip/code_utils.py
codemanip/parse_progress_bar.py
codemanip/py.typed
codemanip/pytest.ini
codemanip/html_code_viewer/__init__.py
codemanip/html_code_viewer/html_code_viewer.py
codemanip/tests/__init__.py
codemanip/tests/code_replacements_test.py
codemanip/tests/code_utils_test.py
litgen/.gitignore
litgen/__init__.py
litgen/code_to_adapted_unit.py
litgen/cpp_port_helper.py
litgen/litgen_generator.py
litgen/options.py
litgen/py.typed
litgen/pyrightconfig.json
litgen/pytest.ini
litgen/cli/__init__.py
litgen/cli/litgen_cli.py
litgen/demo/__init__.py
litgen/demo/litgen_demo.py
litgen/integration_tests/.gitignore
litgen/integration_tests/.gitmodules
litgen/integration_tests/CMakeLists.txt
litgen/integration_tests/Readme.md
litgen/integration_tests/autogenerate_mylib.py
litgen/integration_tests/pyproject.toml
litgen/integration_tests/requirements-dev.txt
litgen/integration_tests/_pydef_nanobind/module.cpp
litgen/integration_tests/_pydef_nanobind/nanobind_mylib.cpp
litgen/integration_tests/_pydef_pybind11/module.cpp
litgen/integration_tests/_pydef_pybind11/pybind_mylib.cpp
litgen/integration_tests/_stubs/lg_mylib/.gitignore
litgen/integration_tests/_stubs/lg_mylib/Readme.md
litgen/integration_tests/_stubs/lg_mylib/__init__.py
litgen/integration_tests/_stubs/lg_mylib/__init__.pyi
litgen/integration_tests/_stubs/lg_mylib/binding.cfg
litgen/integration_tests/_stubs/lg_mylib/py.typed
litgen/integration_tests/_stubs/lg_mylib/use.py
litgen/integration_tests/litgen_cmake/litgen_cmake.cmake
litgen/integration_tests/mylib/_bind_type.h
litgen/integration_tests/mylib/_bind_type.h.pydef.cpp
litgen/integration_tests/mylib/_bind_type.h.pydef_nano.cpp
litgen/integration_tests/mylib/_bind_type.h.pyi
litgen/integration_tests/mylib/basic_test.h
litgen/integration_tests/mylib/basic_test.h.pydef.cpp
litgen/integration_tests/mylib/basic_test.h.pydef_nano.cpp
litgen-0.20.0.dist-info/METADATA
litgen-0.20.0.dist-info/WHEEL
litgen-0.20.0.dist-info/entry_points.txt
litgen-0.20.0.dist-info/licenses/LICENSE.txt
litgen-0.20.0.dist-info/RECORD
