Metadata-Version: 2.3
Name: litgen
Version: 0.20.0
Summary: litgen, aka "Literate Generator", an automatic python bindings generator for humans who like nice code and APIs, based on srcML (https://srcml.org)
Project-URL: homepage, https://pthom.github.io/litgen/
Project-URL: repository, https://github.com/pthom/litgen
Project-URL: documentation, https://pthom.github.io/litgen/
Author-email: Pascal Thomet <pthomet@gmail.com>
Keywords: bindings,c++,code,cpp,generator,pybind11,srcml
Classifier: Development Status :: 4 - Beta
Classifier: Environment :: Console
Classifier: Intended Audience :: Developers
Classifier: Programming Language :: C
Classifier: Programming Language :: C++
Classifier: Programming Language :: Python
Classifier: Topic :: Software Development :: Build Tools
Classifier: Topic :: Software Development :: Documentation
Classifier: Topic :: Software Development :: Libraries :: Python Modules
Classifier: Topic :: Text Processing :: Markup :: XML
Classifier: Typing :: Typed
Requires-Python: >=3.10
Requires-Dist: black
Requires-Dist: fire
Requires-Dist: munch
Requires-Dist: nanobind
Requires-Dist: pybind11
Requires-Dist: srcml-caller
